{
  "favorites": [
    {
      "id": "693134",
      "adult": false,
      "backdrop_path": "/xOMo8BRK7PfcJv9JCnx7s5hj0PX.jpg",
      "genre_ids": [
        878,
        12
      ],
      "original_language": "en",
      "original_title": "Dune: Part Two",
      "overview": "Follow the mythic journey of Paul Atreides as he unites with Chani and the Fremen while on a path of revenge against the conspirators who destroyed his family. Facing a choice between the love of his life and the fate of the known universe, Paul endeavors to prevent a terrible future only he can foresee.",
      "popularity": 1933.355,
      "poster_path": "/1pdfLvkbY9ohJlCjQH2CZjjYVvJ.jpg",
      "release_date": "2024-02-27",
      "title": "Dune: Part Two",
      "video": false,
      "vote_average": 8.351,
      "vote_count": 2572
    },
    {
      "id": "935271",
      "adult": false,
      "backdrop_path": "/9c0lHTXRqDBxeOToVzRu0GArSne.jpg",
      "genre_ids": [
        878,
        28
      ],
      "original_language": "en",
      "original_title": "After the Pandemic",
      "overview": "Set in a post-apocalyptic world where a global airborne pandemic has wiped out 90% of the Earth's population and only the young and immune have endured as scavengers. For Ellie and Quinn, the daily challenges to stay alive are compounded when they become hunted by the merciless Stalkers.",
      "popularity": 1345.924,
      "poster_path": "/p1LbrdJ53dGfEhRopG71akfzOVu.jpg",
      "release_date": "2022-03-01",
      "title": "After the Pandemic",
      "video": false,
      "vote_average": 5.389,
      "vote_count": 27
    },
    {
      "id": "1271947",
      "adult": false,
      "backdrop_path": null,
      "genre_ids": [
        99,
        14
      ],
      "original_language": "en",
      "original_title": "Saudade: The Lisbon I Never Knew",
      "overview": "A love letter from an American soul to the city of Lisbon.",
      "popularity": 0,
      "poster_path": "/y1tPlGG0zRAbCYKN6O8fMHFZRxs.jpg",
      "release_date": "",
      "title": "Saudade: The Lisbon I Never Knew",
      "video": false,
      "vote_average": 10,
      "vote_count": 1
    },
    {
      "id": "1271948",
      "adult": false,
      "backdrop_path": null,
      "genre_ids": [
        18
      ],
      "original_language": "es",
      "original_title": "Que Pronto Se Hace Tarde",
      "overview": "",
      "popularity": 0,
      "poster_path": "/weaLRZ8B8sa8O0HiFugVytZUhQj.jpg",
      "release_date": "2024-04-07",
      "title": "Que Pronto Se Hace Tarde",
      "video": false,
      "vote_average": 10,
      "vote_count": 1
    },
    {
      "id": "1271770",
      "adult": false,
      "backdrop_path": null,
      "genre_ids": [
        18,
        35
      ],
      "original_language": "pt",
      "original_title": "Atraso",
      "overview": "",
      "popularity": 1.4,
      "poster_path": "/v23qqwqeCYmc8z7hoPGnfshtbN9.jpg",
      "release_date": "2024-04-09",
      "title": "Atraso",
      "video": false,
      "vote_average": 10,
      "vote_count": 1
    }
  ]
}